[
    { "name": "ActionsEnvironmentSecret", "type": "resource", "link": "actionsenvironmentsecret" },
    { "name": "ActionsEnvironmentVariable", "type": "resource", "link": "actionsenvironmentvariable" },
    { "name": "ActionsOrganizationOidcSubjectClaimCustomizationTemplate", "type": "resource", "link": "actionsorganizationoidcsubjectclaimcustomizationtemplate" },
    { "name": "ActionsOrganizationPermissions", "type": "resource", "link": "actionsorganizationpermissions" },
    { "name": "ActionsOrganizationSecret", "type": "resource", "link": "actionsorganizationsecret" },
    { "name": "ActionsOrganizationSecretRepositories", "type": "resource", "link": "actionsorganizationsecretrepositories" },
    { "name": "ActionsOrganizationVariable", "type": "resource", "link": "actionsorganizationvariable" },
    { "name": "ActionsRepositoryAccessLevel", "type": "resource", "link": "actionsrepositoryaccesslevel" },
    { "name": "ActionsRepositoryOidcSubjectClaimCustomizationTemplate", "type": "resource", "link": "actionsrepositoryoidcsubjectclaimcustomizationtemplate" },
    { "name": "ActionsRepositoryPermissions", "type": "resource", "link": "actionsrepositorypermissions" },
    { "name": "ActionsRunnerGroup", "type": "resource", "link": "actionsrunnergroup" },
    { "name": "ActionsSecret", "type": "resource", "link": "actionssecret" },
    { "name": "ActionsVariable", "type": "resource", "link": "actionsvariable" },
    { "name": "AppInstallationRepositories", "type": "resource", "link": "appinstallationrepositories" },
    { "name": "AppInstallationRepository", "type": "resource", "link": "appinstallationrepository" },
    { "name": "Branch", "type": "resource", "link": "branch" },
    { "name": "BranchDefault", "type": "resource", "link": "branchdefault" },
    { "name": "BranchProtection", "type": "resource", "link": "branchprotection" },
    { "name": "BranchProtectionV3", "type": "resource", "link": "branchprotectionv3" },
    { "name": "DependabotOrganizationSecret", "type": "resource", "link": "dependabotorganizationsecret" },
    { "name": "DependabotOrganizationSecretRepositories", "type": "resource", "link": "dependabotorganizationsecretrepositories" },
    { "name": "DependabotSecret", "type": "resource", "link": "dependabotsecret" },
    { "name": "EmuGroupMapping", "type": "resource", "link": "emugroupmapping" },
    { "name": "EnterpriseOrganization", "type": "resource", "link": "enterpriseorganization" },
    { "name": "Issue", "type": "resource", "link": "issue" },
    { "name": "IssueLabel", "type": "resource", "link": "issuelabel" },
    { "name": "Membership", "type": "resource", "link": "membership" },
    { "name": "OrganizationBlock", "type": "resource", "link": "organizationblock" },
    { "name": "OrganizationProject", "type": "resource", "link": "organizationproject" },
    { "name": "OrganizationSecurityManager", "type": "resource", "link": "organizationsecuritymanager" },
    { "name": "OrganizationSettings", "type": "resource", "link": "organizationsettings" },
    { "name": "OrganizationWebhook", "type": "resource", "link": "organizationwebhook" },
    { "name": "ProjectCard", "type": "resource", "link": "projectcard" },
    { "name": "ProjectColumn", "type": "resource", "link": "projectcolumn" },
    { "name": "Provider", "type": "resource", "link": "provider" },
    { "name": "Release", "type": "resource", "link": "release" },
    { "name": "Repository", "type": "resource", "link": "repository" },
    { "name": "RepositoryAutolinkReference", "type": "resource", "link": "repositoryautolinkreference" },
    { "name": "RepositoryCollaborator", "type": "resource", "link": "repositorycollaborator" },
    { "name": "RepositoryCollaborators", "type": "resource", "link": "repositorycollaborators" },
    { "name": "RepositoryDeployKey", "type": "resource", "link": "repositorydeploykey" },
    { "name": "RepositoryEnvironment", "type": "resource", "link": "repositoryenvironment" },
    { "name": "RepositoryFile", "type": "resource", "link": "repositoryfile" },
    { "name": "RepositoryMilestone", "type": "resource", "link": "repositorymilestone" },
    { "name": "RepositoryProject", "type": "resource", "link": "repositoryproject" },
    { "name": "RepositoryPullRequest", "type": "resource", "link": "repositorypullrequest" },
    { "name": "RepositoryTagProtection", "type": "resource", "link": "repositorytagprotection" },
    { "name": "RepositoryWebhook", "type": "resource", "link": "repositorywebhook" },
    { "name": "Team", "type": "resource", "link": "team" },
    { "name": "TeamMembers", "type": "resource", "link": "teammembers" },
    { "name": "TeamMembership", "type": "resource", "link": "teammembership" },
    { "name": "TeamRepository", "type": "resource", "link": "teamrepository" },
    { "name": "TeamSettings", "type": "resource", "link": "teamsettings" },
    { "name": "TeamSyncGroupMapping", "type": "resource", "link": "teamsyncgroupmapping" },
    { "name": "UserGpgKey", "type": "resource", "link": "usergpgkey" },
    { "name": "UserInvitationAccepter", "type": "resource", "link": "userinvitationaccepter" },
    { "name": "UserSshKey", "type": "resource", "link": "usersshkey" },
    { "name": "getActionsEnvironmentSecrets", "type": "function", "link": "getactionsenvironmentsecrets" },
    { "name": "getActionsEnvironmentVariables", "type": "function", "link": "getactionsenvironmentvariables" },
    { "name": "getActionsOrganizationOidcSubjectClaimCustomizationTemplate", "type": "function", "link": "getactionsorganizationoidcsubjectclaimcustomizationtemplate" },
    { "name": "getActionsOrganizationPublicKey", "type": "function", "link": "getactionsorganizationpublickey" },
    { "name": "getActionsOrganizationRegistrationToken", "type": "function", "link": "getactionsorganizationregistrationtoken" },
    { "name": "getActionsOrganizationSecrets", "type": "function", "link": "getactionsorganizationsecrets" },
    { "name": "getActionsOrganizationVariables", "type": "function", "link": "getactionsorganizationvariables" },
    { "name": "getActionsPublicKey", "type": "function", "link": "getactionspublickey" },
    { "name": "getActionsRegistrationToken", "type": "function", "link": "getactionsregistrationtoken" },
    { "name": "getActionsRepositoryOidcSubjectClaimCustomizationTemplate", "type": "function", "link": "getactionsrepositoryoidcsubjectclaimcustomizationtemplate" },
    { "name": "getActionsSecrets", "type": "function", "link": "getactionssecrets" },
    { "name": "getActionsVariables", "type": "function", "link": "getactionsvariables" },
    { "name": "getBranch", "type": "function", "link": "getbranch" },
    { "name": "getBranchProtectionRules", "type": "function", "link": "getbranchprotectionrules" },
    { "name": "getCollaborators", "type": "function", "link": "getcollaborators" },
    { "name": "getDependabotOrganizationPublicKey", "type": "function", "link": "getdependabotorganizationpublickey" },
    { "name": "getDependabotOrganizationSecrets", "type": "function", "link": "getdependabotorganizationsecrets" },
    { "name": "getDependabotPublicKey", "type": "function", "link": "getdependabotpublickey" },
    { "name": "getDependabotSecrets", "type": "function", "link": "getdependabotsecrets" },
    { "name": "getEnterprise", "type": "function", "link": "getenterprise" },
    { "name": "getExternalGroups", "type": "function", "link": "getexternalgroups" },
    { "name": "getGithubApp", "type": "function", "link": "getgithubapp" },
    { "name": "getIpRanges", "type": "function", "link": "getipranges" },
    { "name": "getIssueLabels", "type": "function", "link": "getissuelabels" },
    { "name": "getMembership", "type": "function", "link": "getmembership" },
    { "name": "getOrganization", "type": "function", "link": "getorganization" },
    { "name": "getOrganizationIpAllowList", "type": "function", "link": "getorganizationipallowlist" },
    { "name": "getOrganizationTeamSyncGroups", "type": "function", "link": "getorganizationteamsyncgroups" },
    { "name": "getOrganizationTeams", "type": "function", "link": "getorganizationteams" },
    { "name": "getOrganizationWebhooks", "type": "function", "link": "getorganizationwebhooks" },
    { "name": "getRef", "type": "function", "link": "getref" },
    { "name": "getRelease", "type": "function", "link": "getrelease" },
    { "name": "getRepositories", "type": "function", "link": "getrepositories" },
    { "name": "getRepository", "type": "function", "link": "getrepository" },
    { "name": "getRepositoryAutolinkReferences", "type": "function", "link": "getrepositoryautolinkreferences" },
    { "name": "getRepositoryBranches", "type": "function", "link": "getrepositorybranches" },
    { "name": "getRepositoryDeployKeys", "type": "function", "link": "getrepositorydeploykeys" },
    { "name": "getRepositoryEnvironments", "type": "function", "link": "getrepositoryenvironments" },
    { "name": "getRepositoryFile", "type": "function", "link": "getrepositoryfile" },
    { "name": "getRepositoryMilestone", "type": "function", "link": "getrepositorymilestone" },
    { "name": "getRepositoryPullRequest", "type": "function", "link": "getrepositorypullrequest" },
    { "name": "getRepositoryPullRequests", "type": "function", "link": "getrepositorypullrequests" },
    { "name": "getRepositoryTeams", "type": "function", "link": "getrepositoryteams" },
    { "name": "getRepositoryWebhooks", "type": "function", "link": "getrepositorywebhooks" },
    { "name": "getRestApi", "type": "function", "link": "getrestapi" },
    { "name": "getSshKeys", "type": "function", "link": "getsshkeys" },
    { "name": "getTeam", "type": "function", "link": "getteam" },
    { "name": "getTree", "type": "function", "link": "gettree" },
    { "name": "getUser", "type": "function", "link": "getuser" },
    { "name": "getUsers", "type": "function", "link": "getusers" }
]
